pympq/StormLib.dll
pympq/__init__.py
pympq/pympq.cp39-win32.pyd
pympq-0.2.2.dist-info/METADATA
pympq-0.2.2.dist-info/WHEEL
pympq-0.2.2.dist-info/top_level.txt
pympq-0.2.2.dist-info/RECORD
