Metadata-Version: 2.1
Name: pympq
Version: 0.2.2
Summary: python implementation of the stormlib API
Home-page: https://github.com/Median-XL/pympq
Author: Median XL
License: UNKNOWN
Platform: UNKNOWN
Classifier: Environment :: Win32 (MS Windows)
Classifier: Operating System :: Microsoft :: Windows
Classifier: Programming Language :: C++
Classifier: Programming Language :: Python :: Implementation :: CPython
Classifier: Programming Language :: Python :: 3.6
Classifier: Programming Language :: Python :: 3.7
Classifier: Programming Language :: Python :: 3.8
Classifier: Programming Language :: Python :: 3.9
Classifier: Programming Language :: Python :: 3.10
Classifier: Programming Language :: Python :: 3.11
